snitch/__init__.py
snitch/commands.py
snitch/decorators.py
snitch/logging.py
snitch/plugins/__init__.py
snitch/plugins/rhel.py
snitch/server.py
snitch/snitch.py
snitch/state.py
snitch-0.1.0.dist-info/WHEEL
snitch-0.1.0.dist-info/entry_points.txt
snitch-0.1.0.dist-info/METADATA
snitch-0.1.0.dist-info/RECORD
