Metadata-Version: 2.3
Name: snitch
Version: 0.1.0
Summary: Keeping tabs on your systems..
Author: Jacob Callahan
Author-email: Jacob Callahan <jacob.callahan05@gmail.com>
Requires-Python: >=3.12
